{
  "name": "ITempoListener",
  "source": [
    [
      "src/Types.ts",
      181,
      26
    ]
  ],
  "kind": "Typealias",
  "id": 815,
  "comment": "Typescript type: ITempoListener represents a listener created by Tempo class",
  "constructor": [],
  "accessors": [],
  "methods": [],
  "variables": [],
  "properties": [],
  "flags": {},
  "extends": [],
  "implements": [],
  "type_alias": [
    "{ beats:`number",
    "number[]`, continuous:`boolean`, duration:`number`, fn:`Function`, index:`number`, name:`string`, offset:`number`, period:`number` }"
  ]
}